bulkmodel/__init__.py
bulkmodel/apps.py
bulkmodel/ce.py
bulkmodel/helpers.py
bulkmodel/managers.py
bulkmodel/models.py
bulkmodel/queryset.py
bulkmodel/signals.py
bulkmodel/migrations/__init__.py
django_bulkmodel-0.3.0.dist-info/METADATA
django_bulkmodel-0.3.0.dist-info/RECORD
django_bulkmodel-0.3.0.dist-info/WHEEL
django_bulkmodel-0.3.0.dist-info/top_level.txt
