Metadata-Version: 2.1
Name: django-bulkmodel
Version: 0.3.0
Summary: Adds missing features to Django ORM for working with data in bulk operations
Home-page: https://github.com/ailling/django-bulkmodel
Author: Alan Illing
Author-email: alanilling@protonmail.com
License: Apache Software License
Keywords: django,orm,database,bulk,data
Platform: UNKNOWN
Classifier: Environment :: Web Environment
Classifier: Framework :: Django
Classifier: Framework :: Django :: 1.11
Classifier: Intended Audience :: Developers
Classifier: License :: OSI Approved :: Apache Software License
Classifier: Operating System :: OS Independent
Classifier: Programming Language :: Python
Classifier: Programming Language :: Python :: 3.4
Classifier: Programming Language :: Python :: 3.5
Classifier: Programming Language :: Python :: 3.6
Classifier: Topic :: Database
Classifier: Topic :: Database :: Front-Ends
